README.md
setup.py
iopipe_cli/__init__.py
iopipe_cli/_types.py
iopipe_cli/awslambda.py
iopipe_cli/cli.py
iopipe_cli/cli_awslambda.py
iopipe_cli/cli_stack.py
iopipe_cli/combine_dict.py
iopipe_cli/github.py
iopipe_cli/layers.py
iopipe_cli/s3zip.py
iopipe_cli/stack.py
iopipe_cli/utils.py
iopipe_cli.egg-info/PKG-INFO
iopipe_cli.egg-info/SOURCES.txt
iopipe_cli.egg-info/dependency_links.txt
iopipe_cli.egg-info/entry_points.txt
iopipe_cli.egg-info/requires.txt
iopipe_cli.egg-info/top_level.txt
tests/__init__.py
tests/test_awslambda.py