Metadata-Version: 1.2
Name: iopipe-cli
Version: 0.1.7
Summary: cli utility for managing and instrumenting serverless applications
Home-page: https://github.com/iopipe/iopipe-cli
Author: IOpipe
Author-email: dev@iopipe.com
License: UNKNOWN
Platform: UNKNOWN
Requires-Python: >=3.3
